dj_labeler-1.1.0.dist-info/DESCRIPTION.rst
dj_labeler-1.1.0.dist-info/LICENSE.txt
dj_labeler-1.1.0.dist-info/METADATA
dj_labeler-1.1.0.dist-info/RECORD
dj_labeler-1.1.0.dist-info/WHEEL
dj_labeler-1.1.0.dist-info/metadata.json
dj_labeler-1.1.0.dist-info/top_level.txt
labeler/__init__.py
labeler/base.py
labeler/forms.py
labeler/models.py
