Metadata-Version: 2.0
Name: dj-labeler
Version: 1.1.0
Summary: A Django library to externalize translation strings from models and forms.
Home-page: https://github.com/climapulse/dj-labeler
Author: Climapulse NV
Author-email: kevin.wetzels@climapulse.com
License: BSD
Keywords: dj-labeler,django,i18n
Platform: UNKNOWN
Classifier: Development Status :: 5 - Production/Stable
Classifier: Framework :: Django
Classifier: Framework :: Django :: 1.8
Classifier: Framework :: Django :: 1.9
Classifier: Intended Audience :: Developers
Classifier: License :: OSI Approved :: BSD License
Classifier: Natural Language :: English
Classifier: Programming Language :: Python :: 2
Classifier: Programming Language :: Python :: 2.7
Classifier: Programming Language :: Python :: 3
Classifier: Programming Language :: Python :: 3.4
Classifier: Programming Language :: Python :: 3.5
Requires-Dist: Django
